tap_datateer_graphql_api/__init__.py
tap_datateer_graphql_api/client.py
tap_datateer_graphql_api/streams.py
tap_datateer_graphql_api/tap.py
tap_datateer_graphql_api-0.5.2.dist-info/LICENSE
tap_datateer_graphql_api-0.5.2.dist-info/METADATA
tap_datateer_graphql_api-0.5.2.dist-info/WHEEL
tap_datateer_graphql_api-0.5.2.dist-info/entry_points.txt
tap_datateer_graphql_api-0.5.2.dist-info/RECORD
