Metadata-Version: 2.1
Name: tap-datateer-graphql-api
Version: 0.5.2
Summary: `tap-datateer-graphql-api` is a Singer tap for DatateerGraphqlApi, built with the Meltano Singer SDK.
License: Apache-2.0
Keywords: ELT,DatateerGraphqlApi
Author: Datateer Development
Author-email: dev@datateer.com
Requires-Python: >=3.7.1,<4
Classifier: License :: OSI Approved :: Apache Software License
Classifier: Programming Language :: Python :: 3
Classifier: Programming Language :: Python :: 3.8
Classifier: Programming Language :: Python :: 3.9
Classifier: Programming Language :: Python :: 3.10
Classifier: Programming Language :: Python :: 3.11
Classifier: Programming Language :: Python :: 3.12
Classifier: Programming Language :: Python :: 3.13
Provides-Extra: s3
Requires-Dist: fs-s3fs (>=1.1.1,<1.2.0) ; extra == "s3"
Requires-Dist: requests (>=2.31.0,<2.32.0)
Requires-Dist: singer-sdk (>=0.32.0,<0.33.0)
